{"id": "@GrabOfficial", "channel": "Grab Official", "channel_id": "UCHRwhcaTpLX1loIGU1nGosg", "title": "Grab Official", "channel_follower_count": 21, "description": "", "tags": [], "thumbnails": [{"url": "https://yt3.googleusercontent.com/ytc/AIdro_ndsS_yb2_IZXC-dDUo-zksu29oRuvCFpXm6YqaFylWnLc=s900-c-k-c0x00ffffff-no-rj", "height": 900, "width": 900, "id": "0", "resolution": "900x900"}, {"url": "https://yt3.googleusercontent.com/ytc/AIdro_ndsS_yb2_IZXC-dDUo-zksu29oRuvCFpXm6YqaFylWnLc=s0", "id": "avatar_uncropped", "preference": 1}], "uploader_id": "@GrabOfficial", "uploader_url": "https://www.youtube.com/@GrabOfficial", "playlist_count": 0, "uploader": "Grab Official", "channel_url": "https://www.youtube.com/channel/UCHRwhcaTpLX1loIGU1nGosg", "_type": "playlist", "webpage_url": "https://www.youtube.com/@GrabOfficial", "webpage_url_basename": "@GrabOfficial", "webpage_url_domain": "youtube.com", "extractor": "youtube:tab", "extractor_key": "YoutubeTab", "epoch": 1752475574, "_version": {"version": "2025.06.30", "release_git_head": "b0187844988e557c7e1e6bb1aabd4c1176768d86", "repository": "yt-dlp/yt-dlp"}}